[
    {
        "code": "END 101",
        "name": "Endüstri Mühendisliğine Giriş",
        "credit": "2"
    },
    {
        "code": "BİL 141",
        "name": "Bilgisayar Programlama I",
        "credit": "4"
    },
    {
        "code": "MAT 101",
        "name": "Matematik I",
        "credit": "4"
    },
    {
        "code": "FİZ 101",
        "name": "Fizik I",
        "credit": "3"
    },
    {
        "code": "FİZ 101L",
        "name": "Fizik I Laboratuvarı",
        "credit": "1"
    },
    {
        "code": "KİM 101",
        "name": "Genel Kimya",
        "credit": "3"
    },
    {
        "code": "KİM 101L",
        "name": "Genel Kimya Laboratuvarı",
        "credit": "1"
    },
    {
        "code": "TÜR 101",
        "name": "Türk Dili I",
        "credit": "2"
    },
    {
        "code": "İNG 001",
        "name": "İngilizce I",
        "credit": "2"
    },
    {
        "code": "END 106",
        "name": "Veritabanı Yönetimi",
        "credit": "3"
    },
    {
        "code": "MAK 101",
        "name": "Bilgisayar Destekli Teknik Resim I",
        "credit": "3"
    },
    {
        "code": "MAT 102",
        "name": "Matematik II",
        "credit": "4"
    },
    {
        "code": "FİZ 102",
        "name": "Fizik II",
        "credit": "3"
    },
    {
        "code": "FİZ 102L",
        "name": "Fizik II Laboratuvarı",
        "credit": "1"
    },
    {
        "code": "OEG 101",
        "name": "Ortak Eğitime Giriş",
        "credit": "1"
    },
    {
        "code": "TÜR 102",
        "name": "Türk Dili II",
        "credit": "2"
    },
    {
        "code": "İNG 002",
        "name": "İngilizce II",
        "credit": "2"
    },
    {
        "code": "END 213",
        "name": "Olasılık ve İstatistik I",
        "credit": "3"
    },
    {
        "code": "MAT 201",
        "name": "Doğrusal Cebir",
        "credit": "3"
    },
    {
        "code": "İKT 105",
        "name": "Ekonomiye Giriş",
        "credit": "3"
    },
    {
        "code": "İŞL 212",
        "name": "İşletmecilik Bilgisi",
        "credit": "3"
    },
    {
        "code": "AİT 201",
        "name": "Atatürk İlkeleri ve İnkılap Tarihi I",
        "credit": "2"
    },
    {
        "code": "İNG 003",
        "name": "İngilizce Okuma ve Konuşma",
        "credit": "2"
    },
    {
        "code": "END 202",
        "name": "İş Analizi ve Tasarımı",
        "credit": "3"
    },
    {
        "code": "END 214",
        "name": "Olasılık ve İstatistik II",
        "credit": "3"
    },
    {
        "code": "END 294",
        "name": "Yöneylem Araştırması I",
        "credit": "3"
    },
    {
        "code": "MAK 209",
        "name": "Malzeme Bilimi ve İmalat Yöntemleri",
        "credit": "3"
    },
    {
        "code": "MAK 209L",
        "name": "Malzeme Bilimi ve İmalat Yöntemleri Lab.",
        "credit": "1"
    },
    {
        "code": "MAT 202",
        "name": "Diferansiyel Denklemler",
        "credit": "3"
    },
    {
        "code": "AİT 202",
        "name": "Atatürk İlkeleri ve İnkılap Tarihi II",
        "credit": "2"
    },
    {
        "code": "İNG 004",
        "name": "İş Hayatı İçin İngilizce",
        "credit": "2"
    },
    {
        "code": "END 307",
        "name": "Üretim Sistemleri Planlama",
        "credit": "3"
    },
    {
        "code": "END 321",
        "name": "Rassal Modeller",
        "credit": "3"
    },
    {
        "code": "END 395",
        "name": "Yöneylem Araştırması II",
        "credit": "3"
    },
    {
        "code": "İŞL 353",
        "name": "Muhasebe ve Maliyet Muhasebesi",
        "credit": "3"
    },
    {
        "code": "İYD - 1",
        "name": "İkinci Yabancı Dil 1",
        "credit": "3"
    },
    {
        "code": "END 306",
        "name": "Benzetim Sistemleri",
        "credit": "3"
    },
    {
        "code": "END 308",
        "name": "Tesis Tasarımı ve Planlama",
        "credit": "3"
    },
    {
        "code": "END 320",
        "name": "Mühendislik Ekonomisi",
        "credit": "3"
    },
    {
        "code": "END 396",
        "name": "Servis Sistemleri Tasarım ve Planlama",
        "credit": "3"
    },
    {
        "code": "UGİ 315",
        "name": "Girişimcilik ve Liderlik",
        "credit": "2"
    },
    {
        "code": "İYD - 2",
        "name": "İkinci Yabancı Dil 2",
        "credit": "3"
    },
    {
        "code": "END 409",
        "name": "Üretim Bilişim Sistemleri",
        "credit": "3"
    },
    {
        "code": "END 471",
        "name": "Kalite Planlama ve Kontrol",
        "credit": "3"
    },
    {
        "code": "BSD - 1",
        "name": "Bölüm Seçmeli Dersi",
        "credit": "3"
    },
    {
        "code": "ÜSD - 1",
        "name": "Üniversite Seçmeli Ders I",
        "credit": "3"
    },
    {
        "code": "İYD - 3",
        "name": "İkinci Yabancı Dil 3",
        "credit": "3"
    },
    {
        "code": "END 497",
        "name": "Bitirme Tasarım Projesi",
        "credit": "4"
    },
    {
        "code": "FSD - 1",
        "name": "Fakülte Seçmeli Dersi",
        "credit": "3"
    },
    {
        "code": "ÜSD - 2",
        "name": "Üniversite Seçmeli Dersi II",
        "credit": "3"
    },
    {
        "code": "İYD - 4",
        "name": "İkinci Yabancı Dil 4",
        "credit": "3"
    }
]